Metadata-Version: 1.2
Name: uxsdcxx
Version: 0.0.5
Summary: generate PugiXML reader/writer from XSD schema
Home-page: https://github.com/duck2/uxsdcxx
Author: duck2
Author-email: duck2@protonmail.com
License: Apache-2.0
Project-URL: Source Code, https://github.com/duck2/uxsdcxx
Project-URL: Bug Tracker, https://github.com/duck2/uxsdcxx/issues
Platform: UNKNOWN
